cinquis_util/__init__.py
cinquis_util/text_analytics.py
cinquis_util-0.0.6.dist-info/METADATA
cinquis_util-0.0.6.dist-info/WHEEL
cinquis_util-0.0.6.dist-info/licenses/LICENSE
cinquis_util-0.0.6.dist-info/RECORD
