Metadata-Version: 2.1
Name: cinquis_util
Version: 0.0.6
Summary: Code Inquisitor Utilities
Project-URL: Homepage, https://github.com/Moore-Technologies-LLC/cinquis-util
Project-URL: Bug Tracker, https://github.com/Moore-Technologies-LLC/cinquis-util/issues
Author-email: gcc71 <moore938@regis.edu>
License-File: LICENSE
Classifier: License :: OSI Approved :: MIT License
Classifier: Operating System :: OS Independent
Classifier: Programming Language :: Python :: 3
Requires-Python: >=3.7
